dagster_gemini/__init__.py
dagster_gemini/resource.py
dagster_gemini-0.0.4.dist-info/METADATA
dagster_gemini-0.0.4.dist-info/WHEEL
dagster_gemini-0.0.4.dist-info/top_level.txt
dagster_gemini-0.0.4.dist-info/RECORD
