Metadata-Version: 2.4
Name: dagster-gemini
Version: 0.0.4
Summary: Dagster integration with Gemini
Requires-Python: >=3.10
Requires-Dist: dagster>=1.8.0
Requires-Dist: google-generativeai>=0.8.3
